mongokit_ng/__init__.py
mongokit_ng/auth.py
mongokit_ng/cli.py
mongokit_ng/collection.py
mongokit_ng/connection.py
mongokit_ng/cursor.py
mongokit_ng/database.py
mongokit_ng/document.py
mongokit_ng/grid.py
mongokit_ng/helpers.py
mongokit_ng/migration.py
mongokit_ng/mongo_exceptions.py
mongokit_ng/operators.py
mongokit_ng/paginator.py
mongokit_ng/schema_document.py
mongokit_ng/versioned_document.py
mongokit_ng-0.1.1.dist-info/AUTHORS.rst
mongokit_ng-0.1.1.dist-info/LICENSE
mongokit_ng-0.1.1.dist-info/METADATA
mongokit_ng-0.1.1.dist-info/WHEEL
mongokit_ng-0.1.1.dist-info/top_level.txt
mongokit_ng-0.1.1.dist-info/RECORD
