Metadata-Version: 2.1
Name: mongokit-ng
Version: 0.1.1
Summary: mongokit with python3 and pymongo3+
Home-page: https://github.com/Windfarer/mongokit-ng
Author: Windfarer
Author-email: windfarer@gmail.com
License: MIT license
Keywords: mongokit_ng
Platform: UNKNOWN
Classifier: Development Status :: 2 - Pre-Alpha
Classifier: Intended Audience :: Developers
Classifier: License :: OSI Approved :: MIT License
Classifier: Natural Language :: English
Classifier: Programming Language :: Python :: 3
Classifier: Programming Language :: Python :: 3.5
Classifier: Programming Language :: Python :: 3.6
Classifier: Programming Language :: Python :: 3.7
Classifier: Programming Language :: Python :: 3.8
Requires-Python: >=3.5
Requires-Dist: pymongo (>=3.9.0)
